Workbook

Sheet Project Instructions
A1: PR. 1 Fundamental Booster
A2: Topics:
A3: - Relative & Absolute References, Formatting, Data Input
A4: - IF Formulas, Nested IFs, IF with AND/OR
A5: - COUNTIFS, SUMIFS, AVERAGEIFS
A6: - Lookup Functions (VLOOKUP, XLOOKUP, XMATCH)
A7: - INDEX/MATCH for dynamic searches
A8: - TEXT Functions for string manipulations
A9: - INDIRECT and OFFSET for dynamic references
A10: - Date/Time, Math Functions, FILTER function
A12: Main Tasks:
A13: 1. Apply IF formulas to classify student grades. | B13: Completed in 'Students Grade' col H & I
A14: 2. Use COUNTIFS to count students scoring above 60. | B14: Completed in 'Assignments Dashboard'
A15: 3. Use VLOOKUP to find a product price from sales data. | B15: Completed in 'Assignments Dashboard'
A16: 4. Apply XLOOKUP to fetch employee salaries dynamically. | B16: Completed in 'Assignments Dashboard'
A17: 5. Format and analyze date of joining in Employee data. | B17: Completed in 'Employee Data' col F & G
A18: 6. Use FILTER function to extract students with grades above 80. | B18: Completed in 'Assignments Dashboard'
A20: NOTE: The dashboard sheet contains all the isolated formula assignments.

Sheet Students Grade
A1: Student ID | B1: Name | C1: Math | D1: Science | E1: English | F1: Enrollment Date | G1: Total Score | H1: Average Score | I1: Grade (IF) | J1: Math&Sci > 80 (IF/AND)
A2: 1001 | B2: Student 1 | C2: 61 | D2: 48 | E2: 76 | F2: 2018-01-01 00:00:00 | G2: =SUM(C2:E2) -> 185 | H2: =AVERAGE(C2:E2) -> 61.666667 | I2: =IF(H2>=80,"A",IF(H2>=60,"B",IF(H2>=40,"C","F"))) -> B | J2: =IF(AND(C2>80,D2>80),"Yes","No") -> No
A3: 1002 | B3: Student 2 | C3: 78 | D3: 76 | E3: 70 | F3: 2018-06-30 00:00:00 | G3: =SUM(C3:E3) -> 224 | H3: =AVERAGE(C3:E3) -> 74.666667 | I3: =IF(H3>=80,"A",IF(H3>=60,"B",IF(H3>=40,"C","F"))) -> B | J3: =IF(AND(C3>80,D3>80),"Yes","No") -> No
A4: 1003 | B4: Student 3 | C4: 97 | D4: 60 | E4: 51 | F4: 2018-12-27 00:00:00 | G4: =SUM(C4:E4) -> 208 | H4: =AVERAGE(C4:E4) -> 69.333333 | I4: =IF(H4>=80,"A",IF(H4>=60,"B",IF(H4>=40,"C","F"))) -> B | J4: =IF(AND(C4>80,D4>80),"Yes","No") -> No
A5: 1004 | B5: Student 4 | C5: 74 | D5: 55 | E5: 46 | F5: 2019-06-25 00:00:00 | G5: =SUM(C5:E5) -> 175 | H5: =AVERAGE(C5:E5) -> 58.333333 | I5: =IF(H5>=80,"A",IF(H5>=60,"B",IF(H5>=40,"C","F"))) -> C | J5: =IF(AND(C5>80,D5>80),"Yes","No") -> No
A6: 1005 | B6: Student 5 | C6: 68 | D6: 74 | E6: 84 | F6: 2019-12-22 00:00:00 | G6: =SUM(C6:E6) -> 226 | H6: =AVERAGE(C6:E6) -> 75.333333 | I6: =IF(H6>=80,"A",IF(H6>=60,"B",IF(H6>=40,"C","F"))) -> B | J6: =IF(AND(C6>80,D6>80),"Yes","No") -> No
A7: 1006 | B7: Student 6 | C7: 80 | D7: 70 | E7: 65 | F7: 2020-06-19 00:00:00 | G7: =SUM(C7:E7) -> 215 | H7: =AVERAGE(C7:E7) -> 71.666667 | I7: =IF(H7>=80,"A",IF(H7>=60,"B",IF(H7>=40,"C","F"))) -> B | J7: =IF(AND(C7>80,D7>80),"Yes","No") -> No
A8: 1007 | B8: Student 7 | C8: 75 | D8: 47 | E8: 78 | F8: 2020-12-16 00:00:00 | G8: =SUM(C8:E8) -> 200 | H8: =AVERAGE(C8:E8) -> 66.666667 | I8: =IF(H8>=80,"A",IF(H8>=60,"B",IF(H8>=40,"C","F"))) -> B | J8: =IF(AND(C8>80,D8>80),"Yes","No") -> No
A9: 1008 | B9: Student 8 | C9: 94 | D9: 67 | E9: 64 | F9: 2021-06-14 00:00:00 | G9: =SUM(C9:E9) -> 225 | H9: =AVERAGE(C9:E9) -> 75 | I9: =IF(H9>=80,"A",IF(H9>=60,"B",IF(H9>=40,"C","F"))) -> B | J9: =IF(AND(C9>80,D9>80),"Yes","No") -> No
A10: 1009 | B10: Student 9 | C10: 41 | D10: 75 | E10: 56 | F10: 2021-12-11 00:00:00 | G10: =SUM(C10:E10) -> 172 | H10: =AVERAGE(C10:E10) -> 57.333333 | I10: =IF(H10>=80,"A",IF(H10>=60,"B",IF(H10>=40,"C","F"))) -> C | J10: =IF(AND(C10>80,D10>80),"Yes","No") -> No
A11: 1010 | B11: Student 10 | C11: 98 | D11: 54 | E11: 58 | F11: 2022-06-09 00:00:00 | G11: =SUM(C11:E11) -> 210 | H11: =AVERAGE(C11:E11) -> 70 | I11: =IF(H11>=80,"A",IF(H11>=60,"B",IF(H11>=40,"C","F"))) -> B | J11: =IF(AND(C11>80,D11>80),"Yes","No") -> No
A12: 1011 | B12: Student 11 | C12: 73 | D12: 79 | E12: 53 | F12: 2022-12-06 00:00:00 | G12: =SUM(C12:E12) -> 205 | H12: =AVERAGE(C12:E12) -> 68.333333 | I12: =IF(H12>=80,"A",IF(H12>=60,"B",IF(H12>=40,"C","F"))) -> B | J12: =IF(AND(C12>80,D12>80),"Yes","No") -> No
A13: 1012 | B13: Student 12 | C13: 85 | D13: 89 | E13: 79 | F13: 2023-06-04 00:00:00 | G13: =SUM(C13:E13) -> 253 | H13: =AVERAGE(C13:E13) -> 84.333333 | I13: =IF(H13>=80,"A",IF(H13>=60,"B",IF(H13>=40,"C","F"))) -> A | J13: =IF(AND(C13>80,D13>80),"Yes","No") -> Yes
... A21: 1020 | B21: Student 20 | C21: 83 | D21: 92 | E21: 55 | F21: 2027-05-14 00:00:00 | G21: =SUM(C21:E21) -> 230 | H21: =AVERAGE(C21:E21) -> 76.666667 | I21: =IF(H21>=80,"A",IF(H21>=60,"B",IF(H21>=40,"C","F"))) -> B | J21: =IF(AND(C21>80,D21>80),"Yes","No") -> Yes

Sheet Sales Data
A1: Sales ID | B1: Product | C1: Region | D1: Salesperson | E1: Amount | F1: Date | G1: Discount Eligible (IF/OR) | H1: Discount Amt (Math) | I1: Final Amount
A2: 2001 | B2: Keyboard | C2: South | D2: Person 1 | E2: 7048 | F2: 2023-01-01 00:00:00 | G2: =IF(OR(B2="Laptop", E2>25000), "Yes", "No") -> No | H2: =IF(G2="Yes", E2*0.1, 0) -> 0 | I2: =E2-H2 -> 7048
A3: 2002 | B3: Printer | C3: West | D3: Person 2 | E3: 17428 | F3: 2023-01-16 00:00:00 | G3: =IF(OR(B3="Laptop", E3>25000), "Yes", "No") -> No | H3: =IF(G3="Yes", E3*0.1, 0) -> 0 | I3: =E3-H3 -> 17428
A4: 2003 | B4: Mouse | C4: South | D4: Person 3 | E4: 23672 | F4: 2023-01-31 00:00:00 | G4: =IF(OR(B4="Laptop", E4>25000), "Yes", "No") -> No | H4: =IF(G4="Yes", E4*0.1, 0) -> 0 | I4: =E4-H4 -> 23672
A5: 2004 | B5: Printer | C5: East | D5: Person 4 | E5: 5264 | F5: 2023-02-15 00:00:00 | G5: =IF(OR(B5="Laptop", E5>25000), "Yes", "No") -> No | H5: =IF(G5="Yes", E5*0.1, 0) -> 0 | I5: =E5-H5 -> 5264
A6: 2005 | B6: Keyboard | C6: North | D6: Person 5 | E6: 43388 | F6: 2023-03-02 00:00:00 | G6: =IF(OR(B6="Laptop", E6>25000), "Yes", "No") -> Yes | H6: =IF(G6="Yes", E6*0.1, 0) -> 4338.8 | I6: =E6-H6 -> 39049.2
A7: 2006 | B7: Mouse | C7: North | D7: Person 6 | E7: 19757 | F7: 2023-03-17 00:00:00 | G7: =IF(OR(B7="Laptop", E7>25000), "Yes", "No") -> No | H7: =IF(G7="Yes", E7*0.1, 0) -> 0 | I7: =E7-H7 -> 19757
A8: 2007 | B8: Mouse | C8: East | D8: Person 7 | E8: 32058 | F8: 2023-04-01 00:00:00 | G8: =IF(OR(B8="Laptop", E8>25000), "Yes", "No") -> Yes | H8: =IF(G8="Yes", E8*0.1, 0) -> 3205.8 | I8: =E8-H8 -> 28852.2
A9: 2008 | B9: Keyboard | C9: East | D9: Person 8 | E9: 46429 | F9: 2023-04-16 00:00:00 | G9: =IF(OR(B9="Laptop", E9>25000), "Yes", "No") -> Yes | H9: =IF(G9="Yes", E9*0.1, 0) -> 4642.9 | I9: =E9-H9 -> 41786.1
A10: 2009 | B10: Printer | C10: East | D10: Person 9 | E10: 19746 | F10: 2023-05-01 00:00:00 | G10: =IF(OR(B10="Laptop", E10>25000), "Yes", "No") -> No | H10: =IF(G10="Yes", E10*0.1, 0) -> 0 | I10: =E10-H10 -> 19746
A11: 2010 | B11: Keyboard | C11: South | D11: Person 10 | E11: 35185 | F11: 2023-05-16 00:00:00 | G11: =IF(OR(B11="Laptop", E11>25000), "Yes", "No") -> Yes | H11: =IF(G11="Yes", E11*0.1, 0) -> 3518.5 | I11: =E11-H11 -> 31666.5
A12: 2011 | B12: Keyboard | C12: East | D12: Person 11 | E12: 33920 | F12: 2023-05-31 00:00:00 | G12: =IF(OR(B12="Laptop", E12>25000), "Yes", "No") -> Yes | H12: =IF(G12="Yes", E12*0.1, 0) -> 3392 | I12: =E12-H12 -> 30528
A13: 2012 | B13: Monitor | C13: North | D13: Person 12 | E13: 5611 | F13: 2023-06-15 00:00:00 | G13: =IF(OR(B13="Laptop", E13>25000), "Yes", "No") -> No | H13: =IF(G13="Yes", E13*0.1, 0) -> 0 | I13: =E13-H13 -> 5611
... A21: 2020 | B21: Printer | C21: West | D21: Person 20 | E21: 33953 | F21: 2023-10-13 00:00:00 | G21: =IF(OR(B21="Laptop", E21>25000), "Yes", "No") -> Yes | H21: =IF(G21="Yes", E21*0.1, 0) -> 3395.3 | I21: =E21-H21 -> 30557.7

Sheet Employee Data
A1: Employee ID | B1: Name | C1: Department | D1: Salary | E1: Joining Date | F1: First Name (TEXT) | G1: UPPER Name | H1: Tenure in Days (DATE)
A2: 3001 | B2: Employee 1 | C2: Finance | D2: 86766 | E2: 2015-01-01 00:00:00 | F2: =IFERROR(LEFT(B2, FIND(" ", B2)-1), B2) -> Employee | G2: =UPPER(B2) -> EMPLOYEE 1 | H2: =_xlfn.SINGLE(_xlfn.DAYS(TODAY(), DATEVALUE(LEFT(E2, 10)))) -> 4297
A3: 3002 | B3: Employee 2 | C3: Finance | D3: 31943 | E3: 2015-09-08 00:00:00 | F3: =IFERROR(LEFT(B3, FIND(" ", B3)-1), B3) -> Employee | G3: =UPPER(B3) -> EMPLOYEE 2 | H3: =_xlfn.SINGLE(_xlfn.DAYS(TODAY(), DATEVALUE(LEFT(E3, 10)))) -> 4047
A4: 3003 | B4: Employee 3 | C4: HR | D4: 63374 | E4: 2016-05-15 00:00:00 | F4: =IFERROR(LEFT(B4, FIND(" ", B4)-1), B4) -> Employee | G4: =UPPER(B4) -> EMPLOYEE 3 | H4: =_xlfn.SINGLE(_xlfn.DAYS(TODAY(), DATEVALUE(LEFT(E4, 10)))) -> 3797
A5: 3004 | B5: Employee 4 | C5: Finance | D5: 109972 | E5: 2017-01-20 00:00:00 | F5: =IFERROR(LEFT(B5, FIND(" ", B5)-1), B5) -> Employee | G5: =UPPER(B5) -> EMPLOYEE 4 | H5: =_xlfn.SINGLE(_xlfn.DAYS(TODAY(), DATEVALUE(LEFT(E5, 10)))) -> 3547
A6: 3005 | B6: Employee 5 | C6: IT | D6: 54149 | E6: 2017-09-27 00:00:00 | F6: =IFERROR(LEFT(B6, FIND(" ", B6)-1), B6) -> Employee | G6: =UPPER(B6) -> EMPLOYEE 5 | H6: =_xlfn.SINGLE(_xlfn.DAYS(TODAY(), DATEVALUE(LEFT(E6, 10)))) -> 3297
A7: 3006 | B7: Employee 6 | C7: IT | D7: 78689 | E7: 2018-06-04 00:00:00 | F7: =IFERROR(LEFT(B7, FIND(" ", B7)-1), B7) -> Employee | G7: =UPPER(B7) -> EMPLOYEE 6 | H7: =_xlfn.SINGLE(_xlfn.DAYS(TODAY(), DATEVALUE(LEFT(E7, 10)))) -> 3047
A8: 3007 | B8: Employee 7 | C8: Marketing | D8: 35960 | E8: 2019-02-09 00:00:00 | F8: =IFERROR(LEFT(B8, FIND(" ", B8)-1), B8) -> Employee | G8: =UPPER(B8) -> EMPLOYEE 7 | H8: =_xlfn.SINGLE(_xlfn.DAYS(TODAY(), DATEVALUE(LEFT(E8, 10)))) -> 2797
A9: 3008 | B9: Employee 8 | C9: IT | D9: 91659 | E9: 2019-10-17 00:00:00 | F9: =IFERROR(LEFT(B9, FIND(" ", B9)-1), B9) -> Employee | G9: =UPPER(B9) -> EMPLOYEE 8 | H9: =_xlfn.SINGLE(_xlfn.DAYS(TODAY(), DATEVALUE(LEFT(E9, 10)))) -> 2547
A10: 3009 | B10: Employee 9 | C10: IT | D10: 90423 | E10: 2020-06-23 00:00:00 | F10: =IFERROR(LEFT(B10, FIND(" ", B10)-1), B10) -> Employee | G10: =UPPER(B10) -> EMPLOYEE 9 | H10: =_xlfn.SINGLE(_xlfn.DAYS(TODAY(), DATEVALUE(LEFT(E10, 10)))) -> 2297
A11: 3010 | B11: Employee 10 | C11: HR | D11: 107877 | E11: 2021-02-28 00:00:00 | F11: =IFERROR(LEFT(B11, FIND(" ", B11)-1), B11) -> Employee | G11: =UPPER(B11) -> EMPLOYEE 10 | H11: =_xlfn.SINGLE(_xlfn.DAYS(TODAY(), DATEVALUE(LEFT(E11, 10)))) -> 2047
A12: 3011 | B12: Employee 11 | C12: Finance | D12: 107634 | E12: 2021-11-05 00:00:00 | F12: =IFERROR(LEFT(B12, FIND(" ", B12)-1), B12) -> Employee | G12: =UPPER(B12) -> EMPLOYEE 11 | H12: =_xlfn.SINGLE(_xlfn.DAYS(TODAY(), DATEVALUE(LEFT(E12, 10)))) -> 1797
A13: 3012 | B13: Employee 12 | C13: Finance | D13: 35226 | E13: 2022-07-13 00:00:00 | F13: =IFERROR(LEFT(B13, FIND(" ", B13)-1), B13) -> Employee | G13: =UPPER(B13) -> EMPLOYEE 12 | H13: =_xlfn.SINGLE(_xlfn.DAYS(TODAY(), DATEVALUE(LEFT(E13, 10)))) -> 1547
... A21: 3020 | B21: Employee 20 | C21: Marketing | D21: 99924 | E21: 2028-01-03 00:00:00 | F21: =IFERROR(LEFT(B21, FIND(" ", B21)-1), B21) -> Employee | G21: =UPPER(B21) -> EMPLOYEE 20 | H21: =_xlfn.SINGLE(_xlfn.DAYS(TODAY(), DATEVALUE(LEFT(E21, 10)))) -> -453

Sheet Assignments Dashboard
A1: Assignment Category | B1: Description | C1: Formula / Result
A2: IF | B2: Classify student grades | C2: =IF(AVERAGE('Students Grade'!C2:E2)>=80,"A",IF(AVERAGE('Students Grade'!C2:E2)>=60,"B",IF(AVERAGE('Students Grade'!C2:E2)>=40,"C","F"))) -> B
A3: COUNTIFS | B3: Count students scoring above 60 in Math | C3: =COUNTIFS('Students Grade'!C2:C21,">60") -> 19
A4: VLOOKUP | B4: Find product price from Sales Data | C4: =VLOOKUP("Keyboard",'Sales Data'!B2:E21,4,FALSE) -> 7048
A5: XLOOKUP | B5: Fetch employee salary dynamically | C5: =_xlfn.SINGLE(_xlfn.XLOOKUP("Employee 15", 'Employee Data'!B2:B21, 'Employee Data'!D2:D21, "Not Found")) -> 63297
A6: DATE | B6: Format and analyze employee joining date | C6: =_xlfn.SINGLE(_xlfn.DAYS(TODAY(), DATEVALUE(LEFT('Employee Data'!E2, 10)))) -> 4297
A7: FILTER | B7: Extract students with grades above 80 | C7: =_xlfn._xlws.FILTER('Students Grade'!B2:B21,'Students Grade'!H2:H21>80,"No Students") -> Student 12
